[
  "{\"listingBlockerResp\":{\"blockedMessage\":\"\",\"shouldOverrideWhCheck\":false,\"listingBlocked\":false},\"orgSummary\":{\"orgId\":\"ORG61X03TRTDCDHEGPCE0TNV2QFSW\",\"displayName\":\"PRACHI CREATION\",\"ownerUserId\":\"USR7GFFSXJ2XJQ9HZD0GVDGJ1WZFZ\",\"ownerName\":\"Prexa CREATION\",\"yearInception\":2015,\"logoUrl\":\"https://ud-img.azureedge.net/t_im_w240/u/user-media/dugc8lnypk1zw32tthwq.jpg\",\"createdAt\":1508654492406,\"preferredCategories\":[\"clothing\",\"clothing_women\",\"clothing_men\",\"clothing_ethnic\",\"clothing_western\",\"Electronics\",\"clothing_kids\",\"fashion_accessories\",\"clothing_fabric\",\"clothing_home_furnishing\",\"food_and_fmcg\",\"home_and_kitchen\",\"footwear\",\"toy_and_babycare\",\"clothing_innerwear\",\"computers_and_accessories\",\"mobiles_and_accessories\",\"stationary\"],\"preferredContactNumber\":\"+91-7096358008\",\"gstnAvailable\":true,\"gstNumber\":null,\"orgMetrics\":{},\"sellingPrefs\":{\"sellingCategories\":[\"clothing\",\"clothing_women\",\"clothing_ethnic\",\"clothing_western\"],\"minOrderValuePaise\":0,\"generalPolicy\":\"<p>No return... No Exchange... \\nIf damage then return possible.</p>\\n\",\"sellingEnabled\":true},\"orgTypes\":[\"MANUFACTURER\",\"WHOLESALER\",\"DISTRIBUTOR\"],\"location\":\"Ahmedabad, Gujarat\"},\"accessContext\":{\"displayReason\":null,\"accessible\":false},\"listingId\":\"TLCKR1FZ6DY6HETQNWGJ67JMZP889Z1\",\"title\":\"Rayon LONG DESIGNER DOUBLE LAYER KURTIS.  4 COLOUR SET\",\"brand\":\"\",\"platformBlocked\":false,\"status\":\"ACTIVE\",\"vat\":0,\"gst\":500,\"priceIncludesTax\":false,\"vatPercent\":null,\"gstPercent\":\"5.00\",\"hasExtraTaxes\":true,\"priceDiscount\":0,\"priceDiscountBps\":0,\"bulkPricingAvailable\":false,\"availableOnSearch\":true,\"termsAndConditions\":\"\",\"description\":\"<p>Call / whats app 7096358008</p>\\n\",\"minExpireAt\":null,\"maxExpireAt\":null,\"hasSalesUnits\":false,\"tags\":[{\"tagName\":\"offer\",\"tagDisplayName\":\"OFFER\",\"values\":[\"CLTdealofthedayFlatPriceDiscount\"]},{\"tagName\":\"featured\",\"tagDisplayName\":\"FEATURED\",\"values\":[\"CLTdealoftheday\"]}],\"salesUnits\":[],\"specList\":[{\"fieldName\":\"ctg_fabric\",\"fieldDisplayName\":\"Fabric\",\"values\":[\"Rayon\"]},{\"fieldName\":\"ctg_design_style\",\"fieldDisplayName\":\"Clothing Design / Style\",\"values\":[\"Anarkali / Frock / Umbrella Ghera Kurti\",\"Indo-Western Style / Fancy Kurti\",\"Double Layered / Overlay Kurti\",\"Printed Kurti\"]},{\"fieldName\":\"ckr_occasion\",\"fieldDisplayName\":\"Occasion\",\"values\":[\"Casual Wear\",\"Party Wear\",\"Wedding Wear\",\"Summer Wear\",\"Festive Wear\"]},{\"fieldName\":\"ckr_catalog_type\",\"fieldDisplayName\":\"Catalog Type\",\"values\":[\"Color Set\"]},{\"fieldName\":\"size\",\"fieldDisplayName\":\"Size\",\"values\":[\"XL\",\"42\"]},{\"fieldName\":\"collar\",\"fieldDisplayName\":\"Neck/Collar\",\"values\":[\"Round Neck\"]},{\"fieldName\":\"sleeve\",\"fieldDisplayName\":\"Sleeve\",\"values\":[\"Sleeveless\"]},{\"fieldName\":\"ctg_ideal_for\",\"fieldDisplayName\":\"Ideal For\",\"values\":[\"Women\"]}],\"minPricePaise\":null,\"maxPricePaise\":null,\"primaryImageAsset\":{\"id\":\"u/products/0a8qhxpr5o5x8g15oo14.jpg/768/576\",\"original\":{\"uri\":\"https://udaan.azureedge.net/products/0a8qhxpr5o5x8g15oo14.jpg\",\"width\":768,\"height\":576},\"variants\":[{\"uri\":\"https://ud-img.azureedge.net/t_im_h640/u/products/0a8qhxpr5o5x8g15oo14.jpg\",\"width\":768,\"height\":576},{\"uri\":\"https://ud-img.azureedge.net/t_im_w480/u/products/0a8qhxpr5o5x8g15oo14.jpg\",\"width\":480,\"height\":360},{\"uri\":\"https://ud-img.azureedge.net/t_im_w240/u/products/0a8qhxpr5o5x8g15oo14.jpg\",\"width\":240,\"height\":180},{\"uri\":\"https://ud-img.azureedge.net/t_im_h320/u/products/0a8qhxpr5o5x8g15oo14.jpg\",\"width\":427,\"height\":320}]},\"listingVideos\":[],\"listingOrSalesUnitImageAssets\":[{\"id\":\"u/products/0a8qhxpr5o5x8g15oo14.jpg/768/576\",\"original\":{\"uri\":\"https://udaan.azureedge.net/products/0a8qhxpr5o5x8g15oo14.jpg\",\"width\":768,\"height\":576},\"variants\":[{\"uri\":\"https://ud-img.azureedge.net/t_im_h640/u/products/0a8qhxpr5o5x8g15oo14.jpg\",\"width\":768,\"height\":576},{\"uri\":\"https://ud-img.azureedge.net/t_im_w480/u/products/0a8qhxpr5o5x8g15oo14.jpg\",\"width\":480,\"height\":360},{\"uri\":\"https://ud-img.azureedge.net/t_im_w240/u/products/0a8qhxpr5o5x8g15oo14.jpg\",\"width\":240,\"height\":180},{\"uri\":\"https://ud-img.azureedge.net/t_im_h320/u/products/0a8qhxpr5o5x8g15oo14.jpg\",\"width\":427,\"height\":320}]}],\"hasOnlyUniformAssortments\":true,\"hasOnlyAssortments\":true,\"hasNoAssortments\":true,\"listingMoq\":1,\"moqSummary\":1,\"inferredMoq\":null,\"inferredMoqIsFor\":\"pcs\",\"minMrpPaise\":null,\"maxMrpPaise\":null,\"minMarginPercent\":null,\"maxMarginPercent\":null,\"pricesArePer\":\"pc\",\"verticalSummary\":{\"name\":\"ClothingKurta\",\"displayName\":\"Women Kurti\"},\"isBuyable\":false}",
  "{\"listingBlockerResp\":{\"blockedMessage\":\"\",\"shouldOverrideWhCheck\":false,\"listingBlocked\":false},\"orgSummary\":{\"orgId\":\"ORG61X03TRTDCDHEGPCE0TNV2QFSW\",\"displayName\":\"PRACHI CREATION\",\"ownerUserId\":\"USR7GFFSXJ2XJQ9HZD0GVDGJ1WZFZ\",\"ownerName\":\"Prexa CREATION\",\"yearInception\":2015,\"logoUrl\":\"https://ud-img.azureedge.net/t_im_w240/u/user-media/dugc8lnypk1zw32tthwq.jpg\",\"createdAt\":1508654492406,\"preferredCategories\":[\"clothing\",\"clothing_women\",\"clothing_men\",\"clothing_ethnic\",\"clothing_western\",\"Electronics\",\"clothing_kids\",\"fashion_accessories\",\"clothing_fabric\",\"clothing_home_furnishing\",\"food_and_fmcg\",\"home_and_kitchen\",\"footwear\",\"toy_and_babycare\",\"clothing_innerwear\",\"computers_and_accessories\",\"mobiles_and_accessories\",\"stationary\"],\"preferredContactNumber\":\"+91-7096358008\",\"gstnAvailable\":true,\"gstNumber\":null,\"orgMetrics\":{},\"sellingPrefs\":{\"sellingCategories\":[\"clothing\",\"clothing_women\",\"clothing_ethnic\",\"clothing_western\"],\"minOrderValuePaise\":0,\"generalPolicy\":\"<p>No return... No Exchange... \\nIf damage then return possible.</p>\\n\",\"sellingEnabled\":true},\"orgTypes\":[\"MANUFACTURER\",\"WHOLESALER\",\"DISTRIBUTOR\"],\"location\":\"Ahmedabad, Gujarat\"},\"accessContext\":{\"displayReason\":null,\"accessible\":false},\"listingId\":\"TLCKRG69LHLYHKNC72ZHS2368ZSTMBT\",\"title\":\"Rayon LONG DESIGNER DOUBLE LAYER KURTIS.  4 COLOUR SET\",\"brand\":\"\",\"platformBlocked\":false,\"status\":\"ACTIVE\",\"vat\":0,\"gst\":500,\"priceIncludesTax\":false,\"vatPercent\":null,\"gstPercent\":\"5.00\",\"hasExtraTaxes\":true,\"priceDiscount\":0,\"priceDiscountBps\":0,\"bulkPricingAvailable\":false,\"availableOnSearch\":true,\"termsAndConditions\":\"\",\"description\":\"<p>Call / whats app 7096358008</p>\\n\",\"minExpireAt\":null,\"maxExpireAt\":null,\"hasSalesUnits\":false,\"tags\":[{\"tagName\":\"offer\",\"tagDisplayName\":\"OFFER\",\"values\":[\"CLTdealofthedayFlatPriceDiscount\"]},{\"tagName\":\"featured\",\"tagDisplayName\":\"FEATURED\",\"values\":[\"CLTdealoftheday\"]}],\"salesUnits\":[],\"specList\":[{\"fieldName\":\"ctg_fabric\",\"fieldDisplayName\":\"Fabric\",\"values\":[\"Rayon\"]},{\"fieldName\":\"ctg_design_style\",\"fieldDisplayName\":\"Clothing Design / Style\",\"values\":[\"Anarkali / Frock / Umbrella Ghera Kurti\",\"Indo-Western Style / Fancy Kurti\",\"Double Layered / Overlay Kurti\"]},{\"fieldName\":\"ckr_occasion\",\"fieldDisplayName\":\"Occasion\",\"values\":[\"Casual Wear\",\"Party Wear\",\"Wedding Wear\",\"Festive Wear\",\"Summer Wear\"]},{\"fieldName\":\"ckr_catalog_type\",\"fieldDisplayName\":\"Catalog Type\",\"values\":[\"Color Set\"]},{\"fieldName\":\"size\",\"fieldDisplayName\":\"Size\",\"values\":[\"XL\",\"42\"]},{\"fieldName\":\"collar\",\"fieldDisplayName\":\"Neck/Collar\",\"values\":[\"Round Neck\"]},{\"fieldName\":\"sleeve\",\"fieldDisplayName\":\"Sleeve\",\"values\":[\"3/4Th Sleeves\"]},{\"fieldName\":\"ctg_ideal_for\",\"fieldDisplayName\":\"Ideal For\",\"values\":[\"Women\"]}],\"minPricePaise\":null,\"maxPricePaise\":null,\"primaryImageAsset\":{\"id\":\"u/products/z2esnmxn040fgam32o0n.jpg/768/576\",\"original\":{\"uri\":\"https://udaan.azureedge.net/products/z2esnmxn040fgam32o0n.jpg\",\"width\":768,\"height\":576},\"variants\":[{\"uri\":\"https://ud-img.azureedge.net/t_im_h640/u/products/z2esnmxn040fgam32o0n.jpg\",\"width\":768,\"height\":576},{\"uri\":\"https://ud-img.azureedge.net/t_im_w480/u/products/z2esnmxn040fgam32o0n.jpg\",\"width\":480,\"height\":360},{\"uri\":\"https://ud-img.azureedge.net/t_im_w240/u/products/z2esnmxn040fgam32o0n.jpg\",\"width\":240,\"height\":180},{\"uri\":\"https://ud-img.azureedge.net/t_im_h320/u/products/z2esnmxn040fgam32o0n.jpg\",\"width\":427,\"height\":320}]},\"listingVideos\":[],\"listingOrSalesUnitImageAssets\":[{\"id\":\"u/products/z2esnmxn040fgam32o0n.jpg/768/576\",\"original\":{\"uri\":\"https://udaan.azureedge.net/products/z2esnmxn040fgam32o0n.jpg\",\"width\":768,\"height\":576},\"variants\":[{\"uri\":\"https://ud-img.azureedge.net/t_im_h640/u/products/z2esnmxn040fgam32o0n.jpg\",\"width\":768,\"height\":576},{\"uri\":\"https://ud-img.azureedge.net/t_im_w480/u/products/z2esnmxn040fgam32o0n.jpg\",\"width\":480,\"height\":360},{\"uri\":\"https://ud-img.azureedge.net/t_im_w240/u/products/z2esnmxn040fgam32o0n.jpg\",\"width\":240,\"height\":180},{\"uri\":\"https://ud-img.azureedge.net/t_im_h320/u/products/z2esnmxn040fgam32o0n.jpg\",\"width\":427,\"height\":320}]}],\"hasOnlyUniformAssortments\":true,\"hasOnlyAssortments\":true,\"hasNoAssortments\":true,\"listingMoq\":1,\"moqSummary\":1,\"inferredMoq\":null,\"inferredMoqIsFor\":\"pcs\",\"minMrpPaise\":null,\"maxMrpPaise\":null,\"minMarginPercent\":null,\"maxMarginPercent\":null,\"pricesArePer\":\"pc\",\"verticalSummary\":{\"name\":\"ClothingKurta\",\"displayName\":\"Women Kurti\"},\"isBuyable\":false}",
  "{\"listingBlockerResp\":{\"blockedMessage\":\"\",\"shouldOverrideWhCheck\":false,\"listingBlocked\":false},\"orgSummary\":{\"orgId\":\"ORG61X03TRTDCDHEGPCE0TNV2QFSW\",\"displayName\":\"PRACHI CREATION\",\"ownerUserId\":\"USR7GFFSXJ2XJQ9HZD0GVDGJ1WZFZ\",\"ownerName\":\"Prexa CREATION\",\"yearInception\":2015,\"logoUrl\":\"https://ud-img.azureedge.net/t_im_w240/u/user-media/dugc8lnypk1zw32tthwq.jpg\",\"createdAt\":1508654492406,\"preferredCategories\":[\"clothing\",\"clothing_women\",\"clothing_men\",\"clothing_ethnic\",\"clothing_western\",\"Electronics\",\"clothing_kids\",\"fashion_accessories\",\"clothing_fabric\",\"clothing_home_furnishing\",\"food_and_fmcg\",\"home_and_kitchen\",\"footwear\",\"toy_and_babycare\",\"clothing_innerwear\",\"computers_and_accessories\",\"mobiles_and_accessories\",\"stationary\"],\"preferredContactNumber\":\"+91-7096358008\",\"gstnAvailable\":true,\"gstNumber\":null,\"orgMetrics\":{},\"sellingPrefs\":{\"sellingCategories\":[\"clothing\",\"clothing_women\",\"clothing_ethnic\",\"clothing_western\"],\"minOrderValuePaise\":0,\"generalPolicy\":\"<p>No return... No Exchange... \\nIf damage then return possible.</p>\\n\",\"sellingEnabled\":true},\"orgTypes\":[\"MANUFACTURER\",\"WHOLESALER\",\"DISTRIBUTOR\"],\"location\":\"Ahmedabad, Gujarat\"},\"accessContext\":{\"displayReason\":null,\"accessible\":false},\"listingId\":\"TLCKRNZ5EFLPNDT8LWZN51HXYYF6KJJ\",\"title\":\"RAYON LONG DESIGNER DOUBLE LAYER KURTIS.  4 COLOUR SET\",\"brand\":\"\",\"platformBlocked\":false,\"status\":\"ACTIVE\",\"vat\":0,\"gst\":500,\"priceIncludesTax\":false,\"vatPercent\":null,\"gstPercent\":\"5.00\",\"hasExtraTaxes\":true,\"priceDiscount\":0,\"priceDiscountBps\":0,\"bulkPricingAvailable\":false,\"availableOnSearch\":true,\"termsAndConditions\":\"\",\"description\":\"<p>Call / Whats app 7096358008</p>\\n\",\"minExpireAt\":null,\"maxExpireAt\":null,\"hasSalesUnits\":false,\"tags\":[{\"tagName\":\"offer\",\"tagDisplayName\":\"OFFER\",\"values\":[\"CLTdealofthedayFlatPriceDiscount\"]},{\"tagName\":\"featured\",\"tagDisplayName\":\"FEATURED\",\"values\":[\"CLTdealoftheday\"]}],\"salesUnits\":[],\"specList\":[{\"fieldName\":\"ctg_fabric\",\"fieldDisplayName\":\"Fabric\",\"values\":[\"Rayon\"]},{\"fieldName\":\"ctg_design_style\",\"fieldDisplayName\":\"Clothing Design / Style\",\"values\":[\"Anarkali / Frock / Umbrella Ghera Kurti\",\"Indo-Western Style / Fancy Kurti\",\"Double Layered / Overlay Kurti\"]},{\"fieldName\":\"ckr_occasion\",\"fieldDisplayName\":\"Occasion\",\"values\":[\"Casual Wear\",\"Party Wear\",\"Summer Wear\",\"Festive Wear\",\"Wedding Wear\"]},{\"fieldName\":\"ckr_catalog_type\",\"fieldDisplayName\":\"Catalog Type\",\"values\":[\"Color Set\"]},{\"fieldName\":\"size\",\"fieldDisplayName\":\"Size\",\"values\":[\"XL\",\"42\"]},{\"fieldName\":\"collar\",\"fieldDisplayName\":\"Neck/Collar\",\"values\":[\"Round Neck\"]},{\"fieldName\":\"sleeve\",\"fieldDisplayName\":\"Sleeve\",\"values\":[\"3/4Th Sleeves\"]},{\"fieldName\":\"ctg_ideal_for\",\"fieldDisplayName\":\"Ideal For\",\"values\":[\"Women\"]}],\"minPricePaise\":null,\"maxPricePaise\":null,\"primaryImageAsset\":{\"id\":\"u/products/8yvzq0z92pw98v36osax.jpg/768/576\",\"original\":{\"uri\":\"https://udaan.azureedge.net/products/8yvzq0z92pw98v36osax.jpg\",\"width\":768,\"height\":576},\"variants\":[{\"uri\":\"https://ud-img.azureedge.net/t_im_h640/u/products/8yvzq0z92pw98v36osax.jpg\",\"width\":768,\"height\":576},{\"uri\":\"https://ud-img.azureedge.net/t_im_w480/u/products/8yvzq0z92pw98v36osax.jpg\",\"width\":480,\"height\":360},{\"uri\":\"https://ud-img.azureedge.net/t_im_w240/u/products/8yvzq0z92pw98v36osax.jpg\",\"width\":240,\"height\":180},{\"uri\":\"https://ud-img.azureedge.net/t_im_h320/u/products/8yvzq0z92pw98v36osax.jpg\",\"width\":427,\"height\":320}]},\"listingVideos\":[],\"listingOrSalesUnitImageAssets\":[{\"id\":\"u/products/8yvzq0z92pw98v36osax.jpg/768/576\",\"original\":{\"uri\":\"https://udaan.azureedge.net/products/8yvzq0z92pw98v36osax.jpg\",\"width\":768,\"height\":576},\"variants\":[{\"uri\":\"https://ud-img.azureedge.net/t_im_h640/u/products/8yvzq0z92pw98v36osax.jpg\",\"width\":768,\"height\":576},{\"uri\":\"https://ud-img.azureedge.net/t_im_w480/u/products/8yvzq0z92pw98v36osax.jpg\",\"width\":480,\"height\":360},{\"uri\":\"https://ud-img.azureedge.net/t_im_w240/u/products/8yvzq0z92pw98v36osax.jpg\",\"width\":240,\"height\":180},{\"uri\":\"https://ud-img.azureedge.net/t_im_h320/u/products/8yvzq0z92pw98v36osax.jpg\",\"width\":427,\"height\":320}]}],\"hasOnlyUniformAssortments\":true,\"hasOnlyAssortments\":true,\"hasNoAssortments\":true,\"listingMoq\":1,\"moqSummary\":1,\"inferredMoq\":null,\"inferredMoqIsFor\":\"pcs\",\"minMrpPaise\":null,\"maxMrpPaise\":null,\"minMarginPercent\":null,\"maxMarginPercent\":null,\"pricesArePer\":\"pc\",\"verticalSummary\":{\"name\":\"ClothingKurta\",\"displayName\":\"Women Kurti\"},\"isBuyable\":false}",
  "{\"listingBlockerResp\":{\"blockedMessage\":\"\",\"shouldOverrideWhCheck\":false,\"listingBlocked\":false},\"orgSummary\":{\"orgId\":\"ORG1YKKX2HRGQ8TCZMWFVZSH8PFCH\",\"displayName\":\"PRACHI CREATION\",\"ownerUserId\":\"USR29YXS4BPGNQ6NG210L58HKQ0HJ\",\"ownerName\":\"PRACHI CREATION\",\"yearInception\":2017,\"createdAt\":1514460985246,\"logoUrl\":\"https://ud-img.azureedge.net/t_im_w240/u/user-media/wngzkl392ll8qf3nybva.jpg\",\"preferredCategories\":[\"clothing\",\"clothing_women\",\"clothing_western\",\"clothing_kids\",\"clothing_fabric\",\"fashion_accessories\",\"clothing_men\",\"clothing_home_furnishing\",\"toy_and_babycare\",\"home_and_kitchen\",\"stationary\",\"mobiles_and_accessories\",\"computers_and_accessories\",\"clothing_ethnic\"],\"preferredContactNumber\":\"+91-9265234387\",\"gstNumber\":null,\"orgMetrics\":{},\"gstnAvailable\":true,\"orgTypes\":[\"WHOLESALER\",\"MANUFACTURER\"],\"sellingPrefs\":{\"sellingCategories\":[\"clothing_women\"],\"minOrderValuePaise\":0,\"generalPolicy\":\"<p>if damage then return possible.  available size mentioned only</p>\\n\",\"sellingEnabled\":true},\"location\":\"Ahmedabad, Gujarat\"},\"accessContext\":{\"displayReason\":null,\"accessible\":false},\"listingId\":\"TLCKRGTSNGH6V70QNXZP4XK42K1Q8TS\",\"title\":\"14kg RAYON Embroidered KURTIS.  4 COLOUR SET\",\"brand\":\"\",\"platformBlocked\":false,\"status\":\"ACTIVE\",\"vat\":0,\"gst\":500,\"priceIncludesTax\":false,\"vatPercent\":null,\"gstPercent\":\"5.00\",\"hasExtraTaxes\":true,\"priceDiscount\":0,\"priceDiscountBps\":0,\"bulkPricingAvailable\":false,\"availableOnSearch\":true,\"termsAndConditions\":\"\",\"description\":\"<p>Call / whats app 7096358008</p>\\n\",\"maxExpireAt\":null,\"hasSalesUnits\":false,\"minExpireAt\":null,\"tags\":[],\"salesUnits\":[],\"specList\":[{\"fieldName\":\"ctg_fabric\",\"fieldDisplayName\":\"Fabric\",\"values\":[\"Rayon\"]},{\"fieldName\":\"ctg_design_style\",\"fieldDisplayName\":\"Clothing Design / Style\",\"values\":[\"Straight Kurti\",\"Indo-Western Style / Fancy Kurti\",\"Embroidered Work\",\"A-Line Kurti\"]},{\"fieldName\":\"ckr_occasion\",\"fieldDisplayName\":\"Occasion\",\"values\":[\"Casual Wear\",\"Party Wear\",\"Summer Wear\",\"Wedding Wear\",\"Festive Wear\"]},{\"fieldName\":\"ckr_catalog_type\",\"fieldDisplayName\":\"Catalog Type\",\"values\":[\"Color Set\"]},{\"fieldName\":\"size\",\"fieldDisplayName\":\"Size\",\"values\":[\"XL\",\"42\"]},{\"fieldName\":\"collar\",\"fieldDisplayName\":\"Neck/Collar\",\"values\":[\"Round Neck\"]},{\"fieldName\":\"sleeve\",\"fieldDisplayName\":\"Sleeve\",\"values\":[\"3/4Th Sleeves\"]},{\"fieldName\":\"ctg_ideal_for\",\"fieldDisplayName\":\"Ideal For\",\"values\":[\"Women\"]}],\"minPricePaise\":null,\"maxPricePaise\":null,\"primaryImageAsset\":{\"id\":\"u/products/v6tkyzw271zk8lgzbssw.jpg/768/576\",\"original\":{\"uri\":\"https://udaan.azureedge.net/products/v6tkyzw271zk8lgzbssw.jpg\",\"width\":768,\"height\":576},\"variants\":[{\"uri\":\"https://ud-img.azureedge.net/t_im_h640/u/products/v6tkyzw271zk8lgzbssw.jpg\",\"width\":768,\"height\":576},{\"uri\":\"https://ud-img.azureedge.net/t_im_w480/u/products/v6tkyzw271zk8lgzbssw.jpg\",\"width\":480,\"height\":360},{\"uri\":\"https://ud-img.azureedge.net/t_im_w240/u/products/v6tkyzw271zk8lgzbssw.jpg\",\"width\":240,\"height\":180},{\"uri\":\"https://ud-img.azureedge.net/t_im_h320/u/products/v6tkyzw271zk8lgzbssw.jpg\",\"width\":427,\"height\":320}]},\"listingOrSalesUnitImageAssets\":[{\"id\":\"u/products/v6tkyzw271zk8lgzbssw.jpg/768/576\",\"original\":{\"uri\":\"https://udaan.azureedge.net/products/v6tkyzw271zk8lgzbssw.jpg\",\"width\":768,\"height\":576},\"variants\":[{\"uri\":\"https://ud-img.azureedge.net/t_im_h640/u/products/v6tkyzw271zk8lgzbssw.jpg\",\"width\":768,\"height\":576},{\"uri\":\"https://ud-img.azureedge.net/t_im_w480/u/products/v6tkyzw271zk8lgzbssw.jpg\",\"width\":480,\"height\":360},{\"uri\":\"https://ud-img.azureedge.net/t_im_w240/u/products/v6tkyzw271zk8lgzbssw.jpg\",\"width\":240,\"height\":180},{\"uri\":\"https://ud-img.azureedge.net/t_im_h320/u/products/v6tkyzw271zk8lgzbssw.jpg\",\"width\":427,\"height\":320}]}],\"hasOnlyUniformAssortments\":true,\"hasOnlyAssortments\":true,\"hasNoAssortments\":true,\"moqSummary\":1,\"inferredMoq\":null,\"inferredMoqIsFor\":\"pcs\",\"minMrpPaise\":null,\"maxMrpPaise\":null,\"minMarginPercent\":null,\"maxMarginPercent\":null,\"pricesArePer\":\"pc\",\"listingVideos\":[],\"listingMoq\":1,\"verticalSummary\":{\"name\":\"ClothingKurta\",\"displayName\":\"Women Kurti\"},\"isBuyable\":false}",
  "{\"listingBlockerResp\":{\"blockedMessage\":\"\",\"shouldOverrideWhCheck\":false,\"listingBlocked\":false},\"orgSummary\":{\"orgId\":\"ORG1YKKX2HRGQ8TCZMWFVZSH8PFCH\",\"displayName\":\"PRACHI CREATION\",\"ownerUserId\":\"USR29YXS4BPGNQ6NG210L58HKQ0HJ\",\"ownerName\":\"PRACHI CREATION\",\"yearInception\":2017,\"createdAt\":1514460985246,\"logoUrl\":\"https://ud-img.azureedge.net/t_im_w240/u/user-media/wngzkl392ll8qf3nybva.jpg\",\"preferredCategories\":[\"clothing\",\"clothing_women\",\"clothing_western\",\"clothing_kids\",\"clothing_fabric\",\"fashion_accessories\",\"clothing_men\",\"clothing_home_furnishing\",\"toy_and_babycare\",\"home_and_kitchen\",\"stationary\",\"mobiles_and_accessories\",\"computers_and_accessories\",\"clothing_ethnic\"],\"preferredContactNumber\":\"+91-9265234387\",\"gstnAvailable\":true,\"orgTypes\":[\"WHOLESALER\",\"MANUFACTURER\"],\"sellingPrefs\":{\"sellingCategories\":[\"clothing_women\"],\"minOrderValuePaise\":0,\"generalPolicy\":\"<p>if damage then return possible.  available size mentioned only</p>\\n\",\"sellingEnabled\":true},\"gstNumber\":null,\"orgMetrics\":{},\"location\":\"Ahmedabad, Gujarat\"},\"accessContext\":{\"displayReason\":null,\"accessible\":false},\"listingId\":\"TLCKRKQKS4ZGDEXQZRZ82EZ44SNDBN3\",\"title\":\"14kg RAYON Embroidered KURTIS.  (6 piece catalogue)\",\"brand\":\"\",\"platformBlocked\":false,\"status\":\"ACTIVE\",\"vat\":0,\"gst\":500,\"priceIncludesTax\":false,\"vatPercent\":null,\"gstPercent\":\"5.00\",\"hasExtraTaxes\":true,\"priceDiscount\":0,\"priceDiscountBps\":0,\"bulkPricingAvailable\":false,\"availableOnSearch\":true,\"termsAndConditions\":\"\",\"description\":\"<p>Call / Whats app 7096358008</p>\\n\",\"minExpireAt\":null,\"maxExpireAt\":null,\"hasSalesUnits\":false,\"tags\":[],\"salesUnits\":[],\"specList\":[{\"fieldName\":\"ctg_fabric\",\"fieldDisplayName\":\"Fabric\",\"values\":[\"Rayon\"]},{\"fieldName\":\"ctg_design_style\",\"fieldDisplayName\":\"Clothing Design / Style\",\"values\":[\"Straight Kurti\",\"Indo-Western Style / Fancy Kurti\",\"Embroidered Work\"]},{\"fieldName\":\"ckr_occasion\",\"fieldDisplayName\":\"Occasion\",\"values\":[\"Casual Wear\",\"Party Wear\",\"Summer Wear\",\"Wedding Wear\",\"Festive Wear\"]},{\"fieldName\":\"ckr_catalog_type\",\"fieldDisplayName\":\"Catalog Type\",\"values\":[\"Catalog Set\"]},{\"fieldName\":\"size\",\"fieldDisplayName\":\"Size\",\"values\":[\"XL\",\"42\"]},{\"fieldName\":\"collar\",\"fieldDisplayName\":\"Neck/Collar\",\"values\":[\"Round Neck\"]},{\"fieldName\":\"sleeve\",\"fieldDisplayName\":\"Sleeve\",\"values\":[\"3/4Th Sleeves\"]},{\"fieldName\":\"ctg_ideal_for\",\"fieldDisplayName\":\"Ideal For\",\"values\":[\"Women\"]}],\"minPricePaise\":null,\"maxPricePaise\":null,\"primaryImageAsset\":{\"id\":\"u/products/gfn1qf3bfo44t3520tow.jpg/768/576\",\"original\":{\"uri\":\"https://udaan.azureedge.net/products/gfn1qf3bfo44t3520tow.jpg\",\"width\":768,\"height\":576},\"variants\":[{\"uri\":\"https://ud-img.azureedge.net/t_im_h640/u/products/gfn1qf3bfo44t3520tow.jpg\",\"width\":768,\"height\":576},{\"uri\":\"https://ud-img.azureedge.net/t_im_w480/u/products/gfn1qf3bfo44t3520tow.jpg\",\"width\":480,\"height\":360},{\"uri\":\"https://ud-img.azureedge.net/t_im_w240/u/products/gfn1qf3bfo44t3520tow.jpg\",\"width\":240,\"height\":180},{\"uri\":\"https://ud-img.azureedge.net/t_im_h320/u/products/gfn1qf3bfo44t3520tow.jpg\",\"width\":427,\"height\":320}]},\"listingVideos\":[],\"listingOrSalesUnitImageAssets\":[{\"id\":\"u/products/gfn1qf3bfo44t3520tow.jpg/768/576\",\"original\":{\"uri\":\"https://udaan.azureedge.net/products/gfn1qf3bfo44t3520tow.jpg\",\"width\":768,\"height\":576},\"variants\":[{\"uri\":\"https://ud-img.azureedge.net/t_im_h640/u/products/gfn1qf3bfo44t3520tow.jpg\",\"width\":768,\"height\":576},{\"uri\":\"https://ud-img.azureedge.net/t_im_w480/u/products/gfn1qf3bfo44t3520tow.jpg\",\"width\":480,\"height\":360},{\"uri\":\"https://ud-img.azureedge.net/t_im_w240/u/products/gfn1qf3bfo44t3520tow.jpg\",\"width\":240,\"height\":180},{\"uri\":\"https://ud-img.azureedge.net/t_im_h320/u/products/gfn1qf3bfo44t3520tow.jpg\",\"width\":427,\"height\":320}]},{\"id\":\"u/products/hmio3baxmi6evp9706ay.jpg/768/1024\",\"original\":{\"uri\":\"https://udaan.azureedge.net/products/hmio3baxmi6evp9706ay.jpg\",\"width\":768,\"height\":1024},\"variants\":[{\"uri\":\"https://ud-img.azureedge.net/t_im_h1024/u/products/hmio3baxmi6evp9706ay.jpg\",\"width\":768,\"height\":1024},{\"uri\":\"https://ud-img.azureedge.net/t_im_h640/u/products/hmio3baxmi6evp9706ay.jpg\",\"width\":480,\"height\":640},{\"uri\":\"https://ud-img.azureedge.net/t_im_h320/u/products/hmio3baxmi6evp9706ay.jpg\",\"width\":240,\"height\":320}]},{\"id\":\"u/products/itpb5jicem75xplqtzal.jpg/768/1024\",\"original\":{\"uri\":\"https://udaan.azureedge.net/products/itpb5jicem75xplqtzal.jpg\",\"width\":768,\"height\":1024},\"variants\":[{\"uri\":\"https://ud-img.azureedge.net/t_im_h1024/u/products/itpb5jicem75xplqtzal.jpg\",\"width\":768,\"height\":1024},{\"uri\":\"https://ud-img.azureedge.net/t_im_h640/u/products/itpb5jicem75xplqtzal.jpg\",\"width\":480,\"height\":640},{\"uri\":\"https://ud-img.azureedge.net/t_im_h320/u/products/itpb5jicem75xplqtzal.jpg\",\"width\":240,\"height\":320}]},{\"id\":\"u/products/bz4wn0bng00k30pujj3b.jpg/768/1024\",\"original\":{\"uri\":\"https://udaan.azureedge.net/products/bz4wn0bng00k30pujj3b.jpg\",\"width\":768,\"height\":1024},\"variants\":[{\"uri\":\"https://ud-img.azureedge.net/t_im_h1024/u/products/bz4wn0bng00k30pujj3b.jpg\",\"width\":768,\"height\":1024},{\"uri\":\"https://ud-img.azureedge.net/t_im_h640/u/products/bz4wn0bng00k30pujj3b.jpg\",\"width\":480,\"height\":640},{\"uri\":\"https://ud-img.azureedge.net/t_im_h320/u/products/bz4wn0bng00k30pujj3b.jpg\",\"width\":240,\"height\":320}]},{\"id\":\"u/products/c4cc1fv1zkalgyy4hoci.jpg/768/1024\",\"original\":{\"uri\":\"https://udaan.azureedge.net/products/c4cc1fv1zkalgyy4hoci.jpg\",\"width\":768,\"height\":1024},\"variants\":[{\"uri\":\"https://ud-img.azureedge.net/t_im_h1024/u/products/c4cc1fv1zkalgyy4hoci.jpg\",\"width\":768,\"height\":1024},{\"uri\":\"https://ud-img.azureedge.net/t_im_h640/u/products/c4cc1fv1zkalgyy4hoci.jpg\",\"width\":480,\"height\":640},{\"uri\":\"https://ud-img.azureedge.net/t_im_h320/u/products/c4cc1fv1zkalgyy4hoci.jpg\",\"width\":240,\"height\":320}]},{\"id\":\"u/products/ecvi6rh1yj1ucunvgtdq.jpg/768/1024\",\"original\":{\"uri\":\"https://udaan.azureedge.net/products/ecvi6rh1yj1ucunvgtdq.jpg\",\"width\":768,\"height\":1024},\"variants\":[{\"uri\":\"https://ud-img.azureedge.net/t_im_h1024/u/products/ecvi6rh1yj1ucunvgtdq.jpg\",\"width\":768,\"height\":1024},{\"uri\":\"https://ud-img.azureedge.net/t_im_h640/u/products/ecvi6rh1yj1ucunvgtdq.jpg\",\"width\":480,\"height\":640},{\"uri\":\"https://ud-img.azureedge.net/t_im_h320/u/products/ecvi6rh1yj1ucunvgtdq.jpg\",\"width\":240,\"height\":320}]},{\"id\":\"u/products/tn8mlgyx0tfaje0tmq8w.jpg/768/1024\",\"original\":{\"uri\":\"https://udaan.azureedge.net/products/tn8mlgyx0tfaje0tmq8w.jpg\",\"width\":768,\"height\":1024},\"variants\":[{\"uri\":\"https://ud-img.azureedge.net/t_im_h1024/u/products/tn8mlgyx0tfaje0tmq8w.jpg\",\"width\":768,\"height\":1024},{\"uri\":\"https://ud-img.azureedge.net/t_im_h640/u/products/tn8mlgyx0tfaje0tmq8w.jpg\",\"width\":480,\"height\":640},{\"uri\":\"https://ud-img.azureedge.net/t_im_h320/u/products/tn8mlgyx0tfaje0tmq8w.jpg\",\"width\":240,\"height\":320}]}],\"hasOnlyUniformAssortments\":true,\"hasOnlyAssortments\":true,\"hasNoAssortments\":true,\"listingMoq\":1,\"moqSummary\":1,\"inferredMoq\":null,\"inferredMoqIsFor\":\"pcs\",\"minMrpPaise\":null,\"maxMrpPaise\":null,\"minMarginPercent\":null,\"maxMarginPercent\":null,\"pricesArePer\":\"pc\",\"verticalSummary\":{\"name\":\"ClothingKurta\",\"displayName\":\"Women Kurti\"},\"isBuyable\":false}",
  "{\"listingBlockerResp\":{\"blockedMessage\":\"\",\"shouldOverrideWhCheck\":false,\"listingBlocked\":false},\"orgSummary\":{\"orgId\":\"ORG61X03TRTDCDHEGPCE0TNV2QFSW\",\"displayName\":\"PRACHI CREATION\",\"ownerUserId\":\"USR7GFFSXJ2XJQ9HZD0GVDGJ1WZFZ\",\"ownerName\":\"Prexa CREATION\",\"yearInception\":2015,\"logoUrl\":\"https://ud-img.azureedge.net/t_im_w240/u/user-media/dugc8lnypk1zw32tthwq.jpg\",\"createdAt\":1508654492406,\"preferredCategories\":[\"clothing\",\"clothing_women\",\"clothing_men\",\"clothing_ethnic\",\"clothing_western\",\"Electronics\",\"clothing_kids\",\"fashion_accessories\",\"clothing_fabric\",\"clothing_home_furnishing\",\"food_and_fmcg\",\"home_and_kitchen\",\"footwear\",\"toy_and_babycare\",\"clothing_innerwear\",\"computers_and_accessories\",\"mobiles_and_accessories\",\"stationary\"],\"preferredContactNumber\":\"+91-7096358008\",\"gstnAvailable\":true,\"gstNumber\":null,\"orgMetrics\":{},\"sellingPrefs\":{\"sellingCategories\":[\"clothing\",\"clothing_women\",\"clothing_ethnic\",\"clothing_western\"],\"minOrderValuePaise\":0,\"generalPolicy\":\"<p>No return... No Exchange... \\nIf damage then return possible.</p>\\n\",\"sellingEnabled\":true},\"orgTypes\":[\"MANUFACTURER\",\"WHOLESALER\",\"DISTRIBUTOR\"],\"location\":\"Ahmedabad, Gujarat\"},\"accessContext\":{\"displayReason\":null,\"accessible\":false},\"listingId\":\"TLCKRFND86T36G2822G6Q5QLEEGSFZ3\",\"title\":\"14kg RAYON Embroidered KURTIS.  4 COLOUR SET\",\"brand\":\"\",\"platformBlocked\":false,\"status\":\"ACTIVE\",\"vat\":0,\"gst\":500,\"priceIncludesTax\":false,\"vatPercent\":null,\"gstPercent\":\"5.00\",\"hasExtraTaxes\":true,\"priceDiscount\":0,\"priceDiscountBps\":0,\"bulkPricingAvailable\":false,\"availableOnSearch\":true,\"termsAndConditions\":\"\",\"description\":\"<p>Call / whats app 7096358008</p>\\n\",\"minExpireAt\":null,\"maxExpireAt\":null,\"hasSalesUnits\":false,\"tags\":[{\"tagName\":\"offer\",\"tagDisplayName\":\"OFFER\",\"values\":[\"CLTdealofthedayFlatPriceDiscount\"]},{\"tagName\":\"featured\",\"tagDisplayName\":\"FEATURED\",\"values\":[\"CLTdealoftheday\"]}],\"salesUnits\":[],\"specList\":[{\"fieldName\":\"ctg_fabric\",\"fieldDisplayName\":\"Fabric\",\"values\":[\"Rayon\"]},{\"fieldName\":\"ctg_design_style\",\"fieldDisplayName\":\"Clothing Design / Style\",\"values\":[\"Straight Kurti\",\"Indo-Western Style / Fancy Kurti\",\"Embroidered Work\"]},{\"fieldName\":\"ckr_occasion\",\"fieldDisplayName\":\"Occasion\",\"values\":[\"Casual Wear\",\"Party Wear\",\"Wedding Wear\",\"Summer Wear\",\"Festive Wear\"]},{\"fieldName\":\"ckr_catalog_type\",\"fieldDisplayName\":\"Catalog Type\",\"values\":[\"Color Set\"]},{\"fieldName\":\"size\",\"fieldDisplayName\":\"Size\",\"values\":[\"XL\",\"42\"]},{\"fieldName\":\"collar\",\"fieldDisplayName\":\"Neck/Collar\",\"values\":[\"Round / U Neck\"]},{\"fieldName\":\"sleeve\",\"fieldDisplayName\":\"Sleeve\",\"values\":[\"3/4Th Sleeves\"]},{\"fieldName\":\"ctg_ideal_for\",\"fieldDisplayName\":\"Ideal For\",\"values\":[\"Women\"]}],\"minPricePaise\":null,\"maxPricePaise\":null,\"primaryImageAsset\":{\"id\":\"u/products/wkeaypk1nq76062i4o1k.jpg/768/576\",\"original\":{\"uri\":\"https://udaan.azureedge.net/products/wkeaypk1nq76062i4o1k.jpg\",\"width\":768,\"height\":576},\"variants\":[{\"uri\":\"https://ud-img.azureedge.net/t_im_h640/u/products/wkeaypk1nq76062i4o1k.jpg\",\"width\":768,\"height\":576},{\"uri\":\"https://ud-img.azureedge.net/t_im_w480/u/products/wkeaypk1nq76062i4o1k.jpg\",\"width\":480,\"height\":360},{\"uri\":\"https://ud-img.azureedge.net/t_im_w240/u/products/wkeaypk1nq76062i4o1k.jpg\",\"width\":240,\"height\":180},{\"uri\":\"https://ud-img.azureedge.net/t_im_h320/u/products/wkeaypk1nq76062i4o1k.jpg\",\"width\":427,\"height\":320}]},\"listingVideos\":[],\"listingOrSalesUnitImageAssets\":[{\"id\":\"u/products/wkeaypk1nq76062i4o1k.jpg/768/576\",\"original\":{\"uri\":\"https://udaan.azureedge.net/products/wkeaypk1nq76062i4o1k.jpg\",\"width\":768,\"height\":576},\"variants\":[{\"uri\":\"https://ud-img.azureedge.net/t_im_h640/u/products/wkeaypk1nq76062i4o1k.jpg\",\"width\":768,\"height\":576},{\"uri\":\"https://ud-img.azureedge.net/t_im_w480/u/products/wkeaypk1nq76062i4o1k.jpg\",\"width\":480,\"height\":360},{\"uri\":\"https://ud-img.azureedge.net/t_im_w240/u/products/wkeaypk1nq76062i4o1k.jpg\",\"width\":240,\"height\":180},{\"uri\":\"https://ud-img.azureedge.net/t_im_h320/u/products/wkeaypk1nq76062i4o1k.jpg\",\"width\":427,\"height\":320}]}],\"hasOnlyUniformAssortments\":true,\"hasOnlyAssortments\":true,\"hasNoAssortments\":true,\"listingMoq\":1,\"moqSummary\":1,\"inferredMoq\":null,\"inferredMoqIsFor\":\"pcs\",\"minMrpPaise\":null,\"maxMrpPaise\":null,\"minMarginPercent\":null,\"maxMarginPercent\":null,\"pricesArePer\":\"pc\",\"verticalSummary\":{\"name\":\"ClothingKurta\",\"displayName\":\"Women Kurti\"},\"isBuyable\":false}",
  "{\"listingBlockerResp\":{\"blockedMessage\":\"\",\"shouldOverrideWhCheck\":false,\"listingBlocked\":false},\"orgSummary\":{\"orgId\":\"ORG1YKKX2HRGQ8TCZMWFVZSH8PFCH\",\"displayName\":\"PRACHI CREATION\",\"ownerUserId\":\"USR29YXS4BPGNQ6NG210L58HKQ0HJ\",\"ownerName\":\"PRACHI CREATION\",\"yearInception\":2017,\"createdAt\":1514460985246,\"logoUrl\":\"https://ud-img.azureedge.net/t_im_w240/u/user-media/wngzkl392ll8qf3nybva.jpg\",\"preferredCategories\":[\"clothing\",\"clothing_women\",\"clothing_western\",\"clothing_kids\",\"clothing_fabric\",\"fashion_accessories\",\"clothing_men\",\"clothing_home_furnishing\",\"toy_and_babycare\",\"home_and_kitchen\",\"stationary\",\"mobiles_and_accessories\",\"computers_and_accessories\",\"clothing_ethnic\"],\"preferredContactNumber\":\"+91-9265234387\",\"gstNumber\":null,\"orgMetrics\":{},\"gstnAvailable\":true,\"orgTypes\":[\"WHOLESALER\",\"MANUFACTURER\"],\"sellingPrefs\":{\"sellingCategories\":[\"clothing_women\"],\"minOrderValuePaise\":0,\"generalPolicy\":\"<p>if damage then return possible.  available size mentioned only</p>\\n\",\"sellingEnabled\":true},\"location\":\"Ahmedabad, Gujarat\"},\"accessContext\":{\"displayReason\":null,\"accessible\":false},\"listingId\":\"TLCKR4FNGTFZ4Z5QREG4YTGCS4TBGL0\",\"title\":\"Cotton GHERA pattern KURTIS.  3 COLOUR SET\",\"brand\":\"\",\"platformBlocked\":false,\"status\":\"ACTIVE\",\"vat\":0,\"gst\":500,\"priceIncludesTax\":false,\"vatPercent\":null,\"gstPercent\":\"5.00\",\"hasExtraTaxes\":true,\"priceDiscount\":0,\"priceDiscountBps\":0,\"bulkPricingAvailable\":false,\"availableOnSearch\":true,\"termsAndConditions\":\"\",\"description\":\"<p>Call / Whats app 7096358008</p>\\n\",\"maxExpireAt\":null,\"hasSalesUnits\":false,\"minExpireAt\":null,\"tags\":[],\"salesUnits\":[],\"specList\":[{\"fieldName\":\"ctg_fabric\",\"fieldDisplayName\":\"Fabric\",\"values\":[\"Cotton\"]},{\"fieldName\":\"ctg_design_style\",\"fieldDisplayName\":\"Clothing Design / Style\",\"values\":[\"Anarkali / Frock / Umbrella Ghera Kurti\"]},{\"fieldName\":\"ckr_occasion\",\"fieldDisplayName\":\"Occasion\",\"values\":[\"Casual Wear\",\"Summer Wear\",\"Festive Wear\"]},{\"fieldName\":\"ckr_catalog_type\",\"fieldDisplayName\":\"Catalog Type\",\"values\":[\"Color Set\"]},{\"fieldName\":\"size\",\"fieldDisplayName\":\"Size\",\"values\":[\"XL\",\"42\"]},{\"fieldName\":\"collar\",\"fieldDisplayName\":\"Neck/Collar\",\"values\":[\"Round Neck\"]},{\"fieldName\":\"sleeve\",\"fieldDisplayName\":\"Sleeve\",\"values\":[\"Sleeveless\"]},{\"fieldName\":\"ctg_ideal_for\",\"fieldDisplayName\":\"Ideal For\",\"values\":[\"Women\"]}],\"minPricePaise\":null,\"maxPricePaise\":null,\"primaryImageAsset\":{\"id\":\"u/products/jojut7doneozrd2dq5sz.jpg/768/576\",\"original\":{\"uri\":\"https://udaan.azureedge.net/products/jojut7doneozrd2dq5sz.jpg\",\"width\":768,\"height\":576},\"variants\":[{\"uri\":\"https://ud-img.azureedge.net/t_im_h640/u/products/jojut7doneozrd2dq5sz.jpg\",\"width\":768,\"height\":576},{\"uri\":\"https://ud-img.azureedge.net/t_im_w480/u/products/jojut7doneozrd2dq5sz.jpg\",\"width\":480,\"height\":360},{\"uri\":\"https://ud-img.azureedge.net/t_im_w240/u/products/jojut7doneozrd2dq5sz.jpg\",\"width\":240,\"height\":180},{\"uri\":\"https://ud-img.azureedge.net/t_im_h320/u/products/jojut7doneozrd2dq5sz.jpg\",\"width\":427,\"height\":320}]},\"listingOrSalesUnitImageAssets\":[{\"id\":\"u/products/jojut7doneozrd2dq5sz.jpg/768/576\",\"original\":{\"uri\":\"https://udaan.azureedge.net/products/jojut7doneozrd2dq5sz.jpg\",\"width\":768,\"height\":576},\"variants\":[{\"uri\":\"https://ud-img.azureedge.net/t_im_h640/u/products/jojut7doneozrd2dq5sz.jpg\",\"width\":768,\"height\":576},{\"uri\":\"https://ud-img.azureedge.net/t_im_w480/u/products/jojut7doneozrd2dq5sz.jpg\",\"width\":480,\"height\":360},{\"uri\":\"https://ud-img.azureedge.net/t_im_w240/u/products/jojut7doneozrd2dq5sz.jpg\",\"width\":240,\"height\":180},{\"uri\":\"https://ud-img.azureedge.net/t_im_h320/u/products/jojut7doneozrd2dq5sz.jpg\",\"width\":427,\"height\":320}]}],\"hasOnlyUniformAssortments\":true,\"hasOnlyAssortments\":true,\"hasNoAssortments\":true,\"moqSummary\":1,\"inferredMoq\":null,\"inferredMoqIsFor\":\"pcs\",\"minMrpPaise\":null,\"maxMrpPaise\":null,\"minMarginPercent\":null,\"maxMarginPercent\":null,\"pricesArePer\":\"pc\",\"listingVideos\":[],\"listingMoq\":1,\"verticalSummary\":{\"name\":\"ClothingKurta\",\"displayName\":\"Women Kurti\"},\"isBuyable\":false}",
  "{\"listingBlockerResp\":{\"blockedMessage\":\"\",\"shouldOverrideWhCheck\":false,\"listingBlocked\":false},\"orgSummary\":{\"orgId\":\"ORG61X03TRTDCDHEGPCE0TNV2QFSW\",\"displayName\":\"PRACHI CREATION\",\"ownerUserId\":\"USR7GFFSXJ2XJQ9HZD0GVDGJ1WZFZ\",\"ownerName\":\"Prexa CREATION\",\"yearInception\":2015,\"logoUrl\":\"https://ud-img.azureedge.net/t_im_w240/u/user-media/dugc8lnypk1zw32tthwq.jpg\",\"createdAt\":1508654492406,\"preferredCategories\":[\"clothing\",\"clothing_women\",\"clothing_men\",\"clothing_ethnic\",\"clothing_western\",\"Electronics\",\"clothing_kids\",\"fashion_accessories\",\"clothing_fabric\",\"clothing_home_furnishing\",\"food_and_fmcg\",\"home_and_kitchen\",\"footwear\",\"toy_and_babycare\",\"clothing_innerwear\",\"computers_and_accessories\",\"mobiles_and_accessories\",\"stationary\"],\"preferredContactNumber\":\"+91-7096358008\",\"gstnAvailable\":true,\"gstNumber\":null,\"sellingPrefs\":{\"sellingCategories\":[\"clothing\",\"clothing_women\",\"clothing_ethnic\",\"clothing_western\"],\"minOrderValuePaise\":0,\"generalPolicy\":\"<p>No return... No Exchange... \\nIf damage then return possible.</p>\\n\",\"sellingEnabled\":true},\"orgTypes\":[\"MANUFACTURER\",\"WHOLESALER\",\"DISTRIBUTOR\"],\"orgMetrics\":{},\"location\":\"Ahmedabad, Gujarat\"},\"accessContext\":{\"displayReason\":null,\"accessible\":false},\"listingId\":\"TLCKR78EHDJT1PSDMEFWHNT4DBNDE2Y\",\"title\":\"Cotton Embroidered KURTIS.  4 COLOUR SET\",\"brand\":\"\",\"platformBlocked\":false,\"status\":\"ACTIVE\",\"vat\":0,\"gst\":500,\"priceIncludesTax\":false,\"vatPercent\":null,\"gstPercent\":\"5.00\",\"hasExtraTaxes\":true,\"priceDiscount\":0,\"priceDiscountBps\":0,\"bulkPricingAvailable\":false,\"availableOnSearch\":true,\"termsAndConditions\":\"\",\"description\":\"<p>For More Patterns call/ whats app @ 07096358008</p>\\n\",\"maxExpireAt\":null,\"minExpireAt\":null,\"hasSalesUnits\":false,\"tags\":[{\"tagName\":\"offer\",\"tagDisplayName\":\"OFFER\",\"values\":[\"CLTdealofthedayFlatPriceDiscount\"]},{\"tagName\":\"featured\",\"tagDisplayName\":\"FEATURED\",\"values\":[\"CLTdealoftheday\"]}],\"salesUnits\":[],\"specList\":[{\"fieldName\":\"ctg_fabric\",\"fieldDisplayName\":\"Fabric\",\"values\":[\"Cotton\"]},{\"fieldName\":\"ctg_design_style\",\"fieldDisplayName\":\"Clothing Design / Style\",\"values\":[\"Straight Kurti\",\"Indo-Western Style / Fancy Kurti\",\"Embroidered Work\"]},{\"fieldName\":\"ckr_occasion\",\"fieldDisplayName\":\"Occasion\",\"values\":[\"Casual Wear\",\"Festive Wear\",\"Summer Wear\"]},{\"fieldName\":\"ckr_catalog_type\",\"fieldDisplayName\":\"Catalog Type\",\"values\":[\"Color Set\"]},{\"fieldName\":\"size\",\"fieldDisplayName\":\"Size\",\"values\":[\"XL\",\"42\"]},{\"fieldName\":\"collar\",\"fieldDisplayName\":\"Neck/Collar\",\"values\":[\"Round / U Neck\"]},{\"fieldName\":\"sleeve\",\"fieldDisplayName\":\"Sleeve\",\"values\":[\"3/4Th Sleeves\"]},{\"fieldName\":\"ctg_ideal_for\",\"fieldDisplayName\":\"Ideal For\",\"values\":[\"Women\"]}],\"minPricePaise\":null,\"maxPricePaise\":null,\"primaryImageAsset\":{\"id\":\"u/products/vh2pryhibwh8a18dj8dp.jpg/768/576\",\"original\":{\"uri\":\"https://udaan.azureedge.net/products/vh2pryhibwh8a18dj8dp.jpg\",\"width\":768,\"height\":576},\"variants\":[{\"uri\":\"https://ud-img.azureedge.net/t_im_h640/u/products/vh2pryhibwh8a18dj8dp.jpg\",\"width\":768,\"height\":576},{\"uri\":\"https://ud-img.azureedge.net/t_im_w480/u/products/vh2pryhibwh8a18dj8dp.jpg\",\"width\":480,\"height\":360},{\"uri\":\"https://ud-img.azureedge.net/t_im_w240/u/products/vh2pryhibwh8a18dj8dp.jpg\",\"width\":240,\"height\":180},{\"uri\":\"https://ud-img.azureedge.net/t_im_h320/u/products/vh2pryhibwh8a18dj8dp.jpg\",\"width\":427,\"height\":320}]},\"minMrpPaise\":null,\"maxMrpPaise\":null,\"minMarginPercent\":null,\"maxMarginPercent\":null,\"pricesArePer\":\"pc\",\"verticalSummary\":{\"name\":\"ClothingKurta\",\"displayName\":\"Women Kurti\"},\"listingVideos\":[],\"listingOrSalesUnitImageAssets\":[{\"id\":\"u/products/vh2pryhibwh8a18dj8dp.jpg/768/576\",\"original\":{\"uri\":\"https://udaan.azureedge.net/products/vh2pryhibwh8a18dj8dp.jpg\",\"width\":768,\"height\":576},\"variants\":[{\"uri\":\"https://ud-img.azureedge.net/t_im_h640/u/products/vh2pryhibwh8a18dj8dp.jpg\",\"width\":768,\"height\":576},{\"uri\":\"https://ud-img.azureedge.net/t_im_w480/u/products/vh2pryhibwh8a18dj8dp.jpg\",\"width\":480,\"height\":360},{\"uri\":\"https://ud-img.azureedge.net/t_im_w240/u/products/vh2pryhibwh8a18dj8dp.jpg\",\"width\":240,\"height\":180},{\"uri\":\"https://ud-img.azureedge.net/t_im_h320/u/products/vh2pryhibwh8a18dj8dp.jpg\",\"width\":427,\"height\":320}]}],\"hasOnlyUniformAssortments\":true,\"hasOnlyAssortments\":true,\"hasNoAssortments\":true,\"listingMoq\":1,\"moqSummary\":1,\"inferredMoq\":null,\"inferredMoqIsFor\":\"pcs\",\"isBuyable\":false}",
  "{\"listingBlockerResp\":{\"blockedMessage\":\"\",\"shouldOverrideWhCheck\":false,\"listingBlocked\":false},\"orgSummary\":{\"orgId\":\"ORG61X03TRTDCDHEGPCE0TNV2QFSW\",\"displayName\":\"PRACHI CREATION\",\"ownerUserId\":\"USR7GFFSXJ2XJQ9HZD0GVDGJ1WZFZ\",\"ownerName\":\"Prexa CREATION\",\"yearInception\":2015,\"createdAt\":1508654492406,\"logoUrl\":\"https://ud-img.azureedge.net/t_im_w240/u/user-media/dugc8lnypk1zw32tthwq.jpg\",\"preferredCategories\":[\"clothing\",\"clothing_women\",\"clothing_men\",\"clothing_ethnic\",\"clothing_western\",\"Electronics\",\"clothing_kids\",\"fashion_accessories\",\"clothing_fabric\",\"clothing_home_furnishing\",\"food_and_fmcg\",\"home_and_kitchen\",\"footwear\",\"toy_and_babycare\",\"clothing_innerwear\",\"computers_and_accessories\",\"mobiles_and_accessories\",\"stationary\"],\"preferredContactNumber\":\"+91-7096358008\",\"gstnAvailable\":true,\"orgTypes\":[\"MANUFACTURER\",\"WHOLESALER\",\"DISTRIBUTOR\"],\"sellingPrefs\":{\"sellingCategories\":[\"clothing\",\"clothing_women\",\"clothing_ethnic\",\"clothing_western\"],\"minOrderValuePaise\":0,\"generalPolicy\":\"<p>No return... No Exchange... \\nIf damage then return possible.</p>\\n\",\"sellingEnabled\":true},\"gstNumber\":null,\"orgMetrics\":{},\"location\":\"Ahmedabad, Gujarat\"},\"accessContext\":{\"displayReason\":null,\"accessible\":false},\"listingId\":\"TLCKRNCQ3JJKDVC8KJ48M042717ER2S\",\"title\":\"14kg RAYON Embroidered KURTIS.  4 COLOUR SET\",\"brand\":\"\",\"platformBlocked\":false,\"status\":\"ACTIVE\",\"vat\":0,\"gst\":500,\"priceIncludesTax\":false,\"vatPercent\":null,\"gstPercent\":\"5.00\",\"hasExtraTaxes\":true,\"priceDiscount\":0,\"priceDiscountBps\":0,\"bulkPricingAvailable\":false,\"availableOnSearch\":true,\"termsAndConditions\":\"\",\"description\":\"<p>Call / whats app 7096358008</p>\\n\",\"minExpireAt\":null,\"maxExpireAt\":null,\"hasSalesUnits\":false,\"tags\":[{\"tagName\":\"offer\",\"tagDisplayName\":\"OFFER\",\"values\":[\"CLTdealofthedayFlatPriceDiscount\"]},{\"tagName\":\"featured\",\"tagDisplayName\":\"FEATURED\",\"values\":[\"CLTdealoftheday\"]}],\"salesUnits\":[],\"specList\":[{\"fieldName\":\"ctg_ideal_for\",\"fieldDisplayName\":\"Ideal For\",\"values\":[\"Women\"]},{\"fieldName\":\"ctg_fabric\",\"fieldDisplayName\":\"Fabric\",\"values\":[\"Rayon\"]},{\"fieldName\":\"ctg_design_style\",\"fieldDisplayName\":\"Clothing Design / Style\",\"values\":[\"Straight Kurti\",\"Indo-Western Style / Fancy Kurti\",\"Embroidered Work\"]},{\"fieldName\":\"ckr_occasion\",\"fieldDisplayName\":\"Occasion\",\"values\":[\"Casual Wear\",\"Summer Wear\",\"Festive Wear\",\"Wedding Wear\"]},{\"fieldName\":\"ckr_catalog_type\",\"fieldDisplayName\":\"Catalog Type\",\"values\":[\"Color Set\"]},{\"fieldName\":\"size\",\"fieldDisplayName\":\"Size\",\"values\":[\"42\",\"XL\"]},{\"fieldName\":\"collar\",\"fieldDisplayName\":\"Neck/Collar\",\"values\":[\"Round Neck\"]},{\"fieldName\":\"sleeve\",\"fieldDisplayName\":\"Sleeve\",\"values\":[\"3/4Th Sleeves\"]}],\"minPricePaise\":null,\"maxPricePaise\":null,\"primaryImageAsset\":{\"id\":\"u/products/guykpiuoenhxi1vvsq8k.png/720/540\",\"original\":{\"uri\":\"https://udaan.azureedge.net/products/guykpiuoenhxi1vvsq8k.png\",\"width\":720,\"height\":540},\"variants\":[{\"uri\":\"https://ud-img.azureedge.net/t_im_h640/u/products/guykpiuoenhxi1vvsq8k.png\",\"width\":720,\"height\":540},{\"uri\":\"https://ud-img.azureedge.net/t_im_w480/u/products/guykpiuoenhxi1vvsq8k.png\",\"width\":480,\"height\":360},{\"uri\":\"https://ud-img.azureedge.net/t_im_w240/u/products/guykpiuoenhxi1vvsq8k.png\",\"width\":240,\"height\":180},{\"uri\":\"https://ud-img.azureedge.net/t_im_h320/u/products/guykpiuoenhxi1vvsq8k.png\",\"width\":427,\"height\":320}]},\"listingVideos\":[],\"listingOrSalesUnitImageAssets\":[{\"id\":\"u/products/guykpiuoenhxi1vvsq8k.png/720/540\",\"original\":{\"uri\":\"https://udaan.azureedge.net/products/guykpiuoenhxi1vvsq8k.png\",\"width\":720,\"height\":540},\"variants\":[{\"uri\":\"https://ud-img.azureedge.net/t_im_h640/u/products/guykpiuoenhxi1vvsq8k.png\",\"width\":720,\"height\":540},{\"uri\":\"https://ud-img.azureedge.net/t_im_w480/u/products/guykpiuoenhxi1vvsq8k.png\",\"width\":480,\"height\":360},{\"uri\":\"https://ud-img.azureedge.net/t_im_w240/u/products/guykpiuoenhxi1vvsq8k.png\",\"width\":240,\"height\":180},{\"uri\":\"https://ud-img.azureedge.net/t_im_h320/u/products/guykpiuoenhxi1vvsq8k.png\",\"width\":427,\"height\":320}]}],\"hasOnlyUniformAssortments\":true,\"hasOnlyAssortments\":true,\"hasNoAssortments\":true,\"listingMoq\":1,\"moqSummary\":1,\"inferredMoq\":null,\"inferredMoqIsFor\":\"pcs\",\"minMrpPaise\":null,\"maxMrpPaise\":null,\"minMarginPercent\":null,\"maxMarginPercent\":null,\"pricesArePer\":\"pc\",\"verticalSummary\":{\"name\":\"ClothingKurta\",\"displayName\":\"Women Kurti\"},\"isBuyable\":false}",
  "{\"listingBlockerResp\":{\"blockedMessage\":\"\",\"shouldOverrideWhCheck\":false,\"listingBlocked\":false},\"orgSummary\":{\"orgId\":\"ORG1YKKX2HRGQ8TCZMWFVZSH8PFCH\",\"displayName\":\"PRACHI CREATION\",\"ownerUserId\":\"USR29YXS4BPGNQ6NG210L58HKQ0HJ\",\"ownerName\":\"PRACHI CREATION\",\"yearInception\":2017,\"logoUrl\":\"https://ud-img.azureedge.net/t_im_w240/u/user-media/wngzkl392ll8qf3nybva.jpg\",\"createdAt\":1514460985246,\"preferredCategories\":[\"clothing\",\"clothing_women\",\"clothing_western\",\"clothing_kids\",\"clothing_fabric\",\"fashion_accessories\",\"clothing_men\",\"clothing_home_furnishing\",\"toy_and_babycare\",\"home_and_kitchen\",\"stationary\",\"mobiles_and_accessories\",\"computers_and_accessories\",\"clothing_ethnic\"],\"preferredContactNumber\":\"+91-9265234387\",\"gstnAvailable\":true,\"gstNumber\":null,\"sellingPrefs\":{\"sellingCategories\":[\"clothing_women\"],\"minOrderValuePaise\":0,\"generalPolicy\":\"<p>if damage then return possible.  available size mentioned only</p>\\n\",\"sellingEnabled\":true},\"orgTypes\":[\"WHOLESALER\",\"MANUFACTURER\"],\"orgMetrics\":{},\"location\":\"Ahmedabad, Gujarat\"},\"accessContext\":{\"displayReason\":null,\"accessible\":false},\"listingId\":\"TLCKRXJBVV7E94FQ3DGR6HNLBVHMFTQ\",\"title\":\"Rayon LONG DESIGNER DOUBLE LAYER KURTIS.  4 COLOUR SET\",\"brand\":\"\",\"platformBlocked\":false,\"status\":\"ACTIVE\",\"vat\":0,\"gst\":500,\"priceIncludesTax\":false,\"vatPercent\":null,\"gstPercent\":\"5.00\",\"hasExtraTaxes\":true,\"priceDiscount\":0,\"priceDiscountBps\":0,\"bulkPricingAvailable\":false,\"availableOnSearch\":true,\"termsAndConditions\":\"\",\"description\":\"<p>Call / whats app 7096358008</p>\\n\",\"maxExpireAt\":null,\"minExpireAt\":null,\"hasSalesUnits\":false,\"tags\":[],\"salesUnits\":[],\"specList\":[{\"fieldName\":\"ctg_fabric\",\"fieldDisplayName\":\"Fabric\",\"values\":[\"Rayon\"]},{\"fieldName\":\"ctg_design_style\",\"fieldDisplayName\":\"Clothing Design / Style\",\"values\":[\"Anarkali / Frock / Umbrella Ghera Kurti\",\"Indo-Western Style / Fancy Kurti\",\"Double Layered / Overlay Kurti\"]},{\"fieldName\":\"ckr_occasion\",\"fieldDisplayName\":\"Occasion\",\"values\":[\"Casual Wear\",\"Party Wear\",\"Summer Wear\",\"Festive Wear\"]},{\"fieldName\":\"ckr_catalog_type\",\"fieldDisplayName\":\"Catalog Type\",\"values\":[\"Color Set\"]},{\"fieldName\":\"size\",\"fieldDisplayName\":\"Size\",\"values\":[\"XL\",\"42\"]},{\"fieldName\":\"collar\",\"fieldDisplayName\":\"Neck/Collar\",\"values\":[\"Round Neck\"]},{\"fieldName\":\"sleeve\",\"fieldDisplayName\":\"Sleeve\",\"values\":[\"3/4Th Sleeves\"]},{\"fieldName\":\"ctg_ideal_for\",\"fieldDisplayName\":\"Ideal For\",\"values\":[\"Women\"]}],\"minPricePaise\":null,\"maxPricePaise\":null,\"primaryImageAsset\":{\"id\":\"u/products/yzqpdijhdhgb4kvvr3vz.jpg/768/576\",\"original\":{\"uri\":\"https://udaan.azureedge.net/products/yzqpdijhdhgb4kvvr3vz.jpg\",\"width\":768,\"height\":576},\"variants\":[{\"uri\":\"https://ud-img.azureedge.net/t_im_h640/u/products/yzqpdijhdhgb4kvvr3vz.jpg\",\"width\":768,\"height\":576},{\"uri\":\"https://ud-img.azureedge.net/t_im_w480/u/products/yzqpdijhdhgb4kvvr3vz.jpg\",\"width\":480,\"height\":360},{\"uri\":\"https://ud-img.azureedge.net/t_im_w240/u/products/yzqpdijhdhgb4kvvr3vz.jpg\",\"width\":240,\"height\":180},{\"uri\":\"https://ud-img.azureedge.net/t_im_h320/u/products/yzqpdijhdhgb4kvvr3vz.jpg\",\"width\":427,\"height\":320}]},\"minMrpPaise\":null,\"maxMrpPaise\":null,\"minMarginPercent\":null,\"maxMarginPercent\":null,\"pricesArePer\":\"pc\",\"verticalSummary\":{\"name\":\"ClothingKurta\",\"displayName\":\"Women Kurti\"},\"listingVideos\":[],\"listingOrSalesUnitImageAssets\":[{\"id\":\"u/products/yzqpdijhdhgb4kvvr3vz.jpg/768/576\",\"original\":{\"uri\":\"https://udaan.azureedge.net/products/yzqpdijhdhgb4kvvr3vz.jpg\",\"width\":768,\"height\":576},\"variants\":[{\"uri\":\"https://ud-img.azureedge.net/t_im_h640/u/products/yzqpdijhdhgb4kvvr3vz.jpg\",\"width\":768,\"height\":576},{\"uri\":\"https://ud-img.azureedge.net/t_im_w480/u/products/yzqpdijhdhgb4kvvr3vz.jpg\",\"width\":480,\"height\":360},{\"uri\":\"https://ud-img.azureedge.net/t_im_w240/u/products/yzqpdijhdhgb4kvvr3vz.jpg\",\"width\":240,\"height\":180},{\"uri\":\"https://ud-img.azureedge.net/t_im_h320/u/products/yzqpdijhdhgb4kvvr3vz.jpg\",\"width\":427,\"height\":320}]}],\"hasOnlyUniformAssortments\":true,\"hasOnlyAssortments\":true,\"hasNoAssortments\":true,\"listingMoq\":1,\"moqSummary\":1,\"inferredMoq\":null,\"inferredMoqIsFor\":\"pcs\",\"isBuyable\":false}",
  "{\"listingBlockerResp\":{\"blockedMessage\":\"\",\"shouldOverrideWhCheck\":false,\"listingBlocked\":false},\"orgSummary\":{\"orgId\":\"ORG61X03TRTDCDHEGPCE0TNV2QFSW\",\"displayName\":\"PRACHI CREATION\",\"ownerUserId\":\"USR7GFFSXJ2XJQ9HZD0GVDGJ1WZFZ\",\"ownerName\":\"Prexa CREATION\",\"yearInception\":2015,\"logoUrl\":\"https://ud-img.azureedge.net/t_im_w240/u/user-media/dugc8lnypk1zw32tthwq.jpg\",\"createdAt\":1508654492406,\"preferredCategories\":[\"clothing\",\"clothing_women\",\"clothing_men\",\"clothing_ethnic\",\"clothing_western\",\"Electronics\",\"clothing_kids\",\"fashion_accessories\",\"clothing_fabric\",\"clothing_home_furnishing\",\"food_and_fmcg\",\"home_and_kitchen\",\"footwear\",\"toy_and_babycare\",\"clothing_innerwear\",\"computers_and_accessories\",\"mobiles_and_accessories\",\"stationary\"],\"preferredContactNumber\":\"+91-7096358008\",\"gstnAvailable\":true,\"gstNumber\":null,\"orgMetrics\":{},\"sellingPrefs\":{\"sellingCategories\":[\"clothing\",\"clothing_women\",\"clothing_ethnic\",\"clothing_western\"],\"minOrderValuePaise\":0,\"generalPolicy\":\"<p>No return... No Exchange... \\nIf damage then return possible.</p>\\n\",\"sellingEnabled\":true},\"orgTypes\":[\"MANUFACTURER\",\"WHOLESALER\",\"DISTRIBUTOR\"],\"location\":\"Ahmedabad, Gujarat\"},\"accessContext\":{\"displayReason\":null,\"accessible\":false},\"listingId\":\"TLCKR083LLN922SCKBGDYCR8SGZD2ER\",\"title\":\"RAYON LONG DESIGNER DOUBLE LAYER KURTIS.  4 COLOUR SET\",\"brand\":\"\",\"platformBlocked\":false,\"status\":\"ACTIVE\",\"vat\":0,\"gst\":500,\"priceIncludesTax\":false,\"vatPercent\":null,\"gstPercent\":\"5.00\",\"hasExtraTaxes\":true,\"priceDiscount\":0,\"priceDiscountBps\":0,\"bulkPricingAvailable\":false,\"availableOnSearch\":true,\"termsAndConditions\":\"\",\"description\":\"<p>Call / Whats app 7096358008</p>\\n\",\"minExpireAt\":null,\"maxExpireAt\":null,\"hasSalesUnits\":false,\"tags\":[{\"tagName\":\"offer\",\"tagDisplayName\":\"OFFER\",\"values\":[\"CLTdealofthedayFlatPriceDiscount\"]},{\"tagName\":\"featured\",\"tagDisplayName\":\"FEATURED\",\"values\":[\"CLTdealoftheday\"]}],\"salesUnits\":[],\"specList\":[{\"fieldName\":\"ctg_fabric\",\"fieldDisplayName\":\"Fabric\",\"values\":[\"Rayon\"]},{\"fieldName\":\"ctg_design_style\",\"fieldDisplayName\":\"Clothing Design / Style\",\"values\":[\"Anarkali / Frock / Umbrella Ghera Kurti\",\"Indo-Western Style / Fancy Kurti\",\"Double Layered / Overlay Kurti\"]},{\"fieldName\":\"ckr_occasion\",\"fieldDisplayName\":\"Occasion\",\"values\":[\"Casual Wear\",\"Party Wear\",\"Summer Wear\",\"Festive Wear\"]},{\"fieldName\":\"ckr_catalog_type\",\"fieldDisplayName\":\"Catalog Type\",\"values\":[\"Color Set\"]},{\"fieldName\":\"size\",\"fieldDisplayName\":\"Size\",\"values\":[\"XL\",\"42\"]},{\"fieldName\":\"collar\",\"fieldDisplayName\":\"Neck/Collar\",\"values\":[\"Round / U Neck\"]},{\"fieldName\":\"sleeve\",\"fieldDisplayName\":\"Sleeve\",\"values\":[\"Sleeveless\"]},{\"fieldName\":\"ctg_ideal_for\",\"fieldDisplayName\":\"Ideal For\",\"values\":[\"Women\"]}],\"minPricePaise\":null,\"maxPricePaise\":null,\"primaryImageAsset\":{\"id\":\"u/products/ws4xow3fr7nd4tc5b42a.jpg/768/576\",\"original\":{\"uri\":\"https://udaan.azureedge.net/products/ws4xow3fr7nd4tc5b42a.jpg\",\"width\":768,\"height\":576},\"variants\":[{\"uri\":\"https://ud-img.azureedge.net/t_im_h640/u/products/ws4xow3fr7nd4tc5b42a.jpg\",\"width\":768,\"height\":576},{\"uri\":\"https://ud-img.azureedge.net/t_im_w480/u/products/ws4xow3fr7nd4tc5b42a.jpg\",\"width\":480,\"height\":360},{\"uri\":\"https://ud-img.azureedge.net/t_im_w240/u/products/ws4xow3fr7nd4tc5b42a.jpg\",\"width\":240,\"height\":180},{\"uri\":\"https://ud-img.azureedge.net/t_im_h320/u/products/ws4xow3fr7nd4tc5b42a.jpg\",\"width\":427,\"height\":320}]},\"listingVideos\":[],\"listingOrSalesUnitImageAssets\":[{\"id\":\"u/products/ws4xow3fr7nd4tc5b42a.jpg/768/576\",\"original\":{\"uri\":\"https://udaan.azureedge.net/products/ws4xow3fr7nd4tc5b42a.jpg\",\"width\":768,\"height\":576},\"variants\":[{\"uri\":\"https://ud-img.azureedge.net/t_im_h640/u/products/ws4xow3fr7nd4tc5b42a.jpg\",\"width\":768,\"height\":576},{\"uri\":\"https://ud-img.azureedge.net/t_im_w480/u/products/ws4xow3fr7nd4tc5b42a.jpg\",\"width\":480,\"height\":360},{\"uri\":\"https://ud-img.azureedge.net/t_im_w240/u/products/ws4xow3fr7nd4tc5b42a.jpg\",\"width\":240,\"height\":180},{\"uri\":\"https://ud-img.azureedge.net/t_im_h320/u/products/ws4xow3fr7nd4tc5b42a.jpg\",\"width\":427,\"height\":320}]}],\"hasOnlyUniformAssortments\":true,\"hasOnlyAssortments\":true,\"hasNoAssortments\":true,\"listingMoq\":1,\"moqSummary\":1,\"inferredMoq\":null,\"inferredMoqIsFor\":\"pcs\",\"minMrpPaise\":null,\"maxMrpPaise\":null,\"minMarginPercent\":null,\"maxMarginPercent\":null,\"pricesArePer\":\"pc\",\"verticalSummary\":{\"name\":\"ClothingKurta\",\"displayName\":\"Women Kurti\"},\"isBuyable\":false}",
  "{\"listingBlockerResp\":{\"blockedMessage\":\"\",\"shouldOverrideWhCheck\":false,\"listingBlocked\":false},\"orgSummary\":{\"orgId\":\"ORG1YKKX2HRGQ8TCZMWFVZSH8PFCH\",\"displayName\":\"PRACHI CREATION\",\"ownerUserId\":\"USR29YXS4BPGNQ6NG210L58HKQ0HJ\",\"ownerName\":\"PRACHI CREATION\",\"yearInception\":2017,\"createdAt\":1514460985246,\"logoUrl\":\"https://ud-img.azureedge.net/t_im_w240/u/user-media/wngzkl392ll8qf3nybva.jpg\",\"preferredCategories\":[\"clothing\",\"clothing_women\",\"clothing_western\",\"clothing_kids\",\"clothing_fabric\",\"fashion_accessories\",\"clothing_men\",\"clothing_home_furnishing\",\"toy_and_babycare\",\"home_and_kitchen\",\"stationary\",\"mobiles_and_accessories\",\"computers_and_accessories\",\"clothing_ethnic\"],\"preferredContactNumber\":\"+91-9265234387\",\"gstNumber\":null,\"orgMetrics\":{},\"gstnAvailable\":true,\"orgTypes\":[\"WHOLESALER\",\"MANUFACTURER\"],\"sellingPrefs\":{\"sellingCategories\":[\"clothing_women\"],\"minOrderValuePaise\":0,\"generalPolicy\":\"<p>if damage then return possible.  available size mentioned only</p>\\n\",\"sellingEnabled\":true},\"location\":\"Ahmedabad, Gujarat\"},\"accessContext\":{\"displayReason\":null,\"accessible\":false},\"listingId\":\"TLCKRFFH3H77DDSQ5QZ0RGQPXJTW3R3\",\"title\":\"Cotton DOUBLE LAYER KURTIS.  4 COLOUR SET\",\"brand\":\"\",\"platformBlocked\":false,\"status\":\"ACTIVE\",\"vat\":0,\"gst\":500,\"priceIncludesTax\":false,\"vatPercent\":null,\"gstPercent\":\"5.00\",\"hasExtraTaxes\":true,\"priceDiscount\":0,\"priceDiscountBps\":0,\"bulkPricingAvailable\":false,\"availableOnSearch\":true,\"termsAndConditions\":\"\",\"description\":\"<p>Call / Whats app 7096358008</p>\\n\",\"maxExpireAt\":null,\"hasSalesUnits\":false,\"minExpireAt\":null,\"tags\":[],\"salesUnits\":[],\"specList\":[{\"fieldName\":\"ctg_fabric\",\"fieldDisplayName\":\"Fabric\",\"values\":[\"Cotton\"]},{\"fieldName\":\"ctg_design_style\",\"fieldDisplayName\":\"Clothing Design / Style\",\"values\":[\"Anarkali / Frock / Umbrella Ghera Kurti\",\"Indo-Western Style / Fancy Kurti\",\"Double Layered / Overlay Kurti\"]},{\"fieldName\":\"ckr_occasion\",\"fieldDisplayName\":\"Occasion\",\"values\":[\"Casual Wear\",\"Summer Wear\",\"Festive Wear\",\"Wedding Wear\"]},{\"fieldName\":\"ckr_catalog_type\",\"fieldDisplayName\":\"Catalog Type\",\"values\":[\"Color Set\"]},{\"fieldName\":\"size\",\"fieldDisplayName\":\"Size\",\"values\":[\"XL\",\"42\"]},{\"fieldName\":\"collar\",\"fieldDisplayName\":\"Neck/Collar\",\"values\":[\"Round Neck\"]},{\"fieldName\":\"sleeve\",\"fieldDisplayName\":\"Sleeve\",\"values\":[\"3/4Th Sleeves\"]},{\"fieldName\":\"ctg_ideal_for\",\"fieldDisplayName\":\"Ideal For\",\"values\":[\"Women\"]}],\"minPricePaise\":null,\"maxPricePaise\":null,\"primaryImageAsset\":{\"id\":\"u/products/whniichxezceqobe7l3b.jpg/768/576\",\"original\":{\"uri\":\"https://udaan.azureedge.net/products/whniichxezceqobe7l3b.jpg\",\"width\":768,\"height\":576},\"variants\":[{\"uri\":\"https://ud-img.azureedge.net/t_im_h640/u/products/whniichxezceqobe7l3b.jpg\",\"width\":768,\"height\":576},{\"uri\":\"https://ud-img.azureedge.net/t_im_w480/u/products/whniichxezceqobe7l3b.jpg\",\"width\":480,\"height\":360},{\"uri\":\"https://ud-img.azureedge.net/t_im_w240/u/products/whniichxezceqobe7l3b.jpg\",\"width\":240,\"height\":180},{\"uri\":\"https://ud-img.azureedge.net/t_im_h320/u/products/whniichxezceqobe7l3b.jpg\",\"width\":427,\"height\":320}]},\"listingOrSalesUnitImageAssets\":[{\"id\":\"u/products/whniichxezceqobe7l3b.jpg/768/576\",\"original\":{\"uri\":\"https://udaan.azureedge.net/products/whniichxezceqobe7l3b.jpg\",\"width\":768,\"height\":576},\"variants\":[{\"uri\":\"https://ud-img.azureedge.net/t_im_h640/u/products/whniichxezceqobe7l3b.jpg\",\"width\":768,\"height\":576},{\"uri\":\"https://ud-img.azureedge.net/t_im_w480/u/products/whniichxezceqobe7l3b.jpg\",\"width\":480,\"height\":360},{\"uri\":\"https://ud-img.azureedge.net/t_im_w240/u/products/whniichxezceqobe7l3b.jpg\",\"width\":240,\"height\":180},{\"uri\":\"https://ud-img.azureedge.net/t_im_h320/u/products/whniichxezceqobe7l3b.jpg\",\"width\":427,\"height\":320}]}],\"hasOnlyUniformAssortments\":true,\"hasOnlyAssortments\":true,\"hasNoAssortments\":true,\"moqSummary\":1,\"inferredMoq\":null,\"inferredMoqIsFor\":\"pcs\",\"minMrpPaise\":null,\"maxMrpPaise\":null,\"minMarginPercent\":null,\"maxMarginPercent\":null,\"pricesArePer\":\"pc\",\"listingVideos\":[],\"listingMoq\":1,\"verticalSummary\":{\"name\":\"ClothingKurta\",\"displayName\":\"Women Kurti\"},\"isBuyable\":false}"
]